refo/__init__.py
refo/instructions.py
refo/match.py
refo/patterns.py
refo/virtualmachine.py
fenixrefo-0.13.1.dist-info/LICENSE.txt
fenixrefo-0.13.1.dist-info/METADATA
fenixrefo-0.13.1.dist-info/WHEEL
fenixrefo-0.13.1.dist-info/RECORD
